{
  "_class": "symbolInstance",
  "booleanOperation": -1,
  "clippingMaskMode": 0,
  "do_objectID": "72616814-D6C4-4A20-9C5D-42F45AEF9B97",
  "exportOptions": {
    "_class": "exportOptions",
    "do_objectID": "2ECDFF23-5597-4CAA-85D0-38DF81A09B5C",
    "exportFormats": [
    ],
    "includedLayerIds": [
    ],
    "layerOptions": 0,
    "shouldTrim": false
  },
  "frame": {
    "_class": "rect",
    "constrainProportions": false,
    "do_objectID": "458C376D-D5DA-4565-A7D2-81D5336AF4CF",
    "height": 16,
    "width": 384,
    "x": 48,
    "y": 312
  },
  "hasClippingMask": false,
  "horizontalSpacing": 0,
  "isFixedToViewport": false,
  "isFlippedHorizontal": false,
  "isFlippedVertical": false,
  "isLocked": false,
  "isVisible": true,
  "layerListExpandedType": 0,
  "name": "Item 1",
  "nameIsFixed": true,
  "overrideValues": [
    {
      "_class": "overrideValue",
      "do_objectID": "6E8B99DE-199B-4A32-8C00-4212D06B9B41",
      "overrideName": "C8803D95-B867-43CC-AD2F-25E99180C301_stringValue",
      "value": "Apple"
    }
  ],
  "resizingConstraint": 10,
  "resizingType": 0,
  "rotation": 0,
  "scale": 1,
  "shouldBreakMaskChain": false,
  "style": {
    "_class": "style",
    "do_objectID": "B8EBB82B-ADA5-480C-9E14-C66B6C06F186",
    "endMarkerType": 0,
    "miterLimit": 10,
    "startMarkerType": 0,
    "windingRule": 1
  },
  "symbolID": "C5256EBC-8B29-4963-A157-C034023B4679",
  "userInfo": {
    "com.animaapp.stc-sketch-plugin": {
      "kModelPropertiesKey": {
      }
    }
  },
  "verticalSpacing": 0
}