{
  "_class": "text",
  "attributedString": {
    "_class": "attributedString",
    "attributes": [
      {
        "_class": "stringAttribute",
        "attributes": {
          "MSAttributedStringColorAttribute": {
            "_class": "color",
            "alpha": 1,
            "blue": 0.3333333333333333,
            "green": 0.3333333333333333,
            "red": 0.3333333333333333
          },
          "MSAttributedStringFontAttribute": {
            "_class": "fontDescriptor",
            "attributes": {
              "name": "OpenSans",
              "size": 12
            }
          },
          "paragraphStyle": {
            "_class": "paragraphStyle",
            "alignment": 0,
            "maximumLineHeight": 16,
            "minimumLineHeight": 16
          },
          "textStyleVerticalAlignmentKey": 0
        },
        "length": 10,
        "location": 0
      }
    ],
    "string": "Menu title"
  },
  "automaticallyDrawOnUnderlyingPath": false,
  "booleanOperation": -1,
  "clippingMaskMode": 0,
  "do_objectID": "9DA87270-B708-4389-A1FB-E892B41EF867",
  "dontSynchroniseWithSymbol": false,
  "exportOptions": {
    "_class": "exportOptions",
    "do_objectID": "500EC418-2196-4379-94E2-842919253D6F",
    "exportFormats": [
    ],
    "includedLayerIds": [
    ],
    "layerOptions": 0,
    "shouldTrim": false
  },
  "frame": {
    "_class": "rect",
    "constrainProportions": false,
    "do_objectID": "43AD4C98-F6F0-4A72-9EB3-DAF323538443",
    "height": 16,
    "width": 57,
    "x": 96,
    "y": 16
  },
  "glyphBounds": "{{1, 3}, {56, 11}}",
  "hasClippingMask": false,
  "isFixedToViewport": false,
  "isFlippedHorizontal": false,
  "isFlippedVertical": false,
  "isLocked": false,
  "isVisible": true,
  "layerListExpandedType": 0,
  "lineSpacingBehaviour": 2,
  "name": "Menu title",
  "nameIsFixed": false,
  "resizingConstraint": 2,
  "resizingType": 0,
  "rotation": 0,
  "sharedStyleID": "8972F355-1590-4455-AA7A-DEA2934D6561",
  "shouldBreakMaskChain": false,
  "style": {
    "_class": "style",
    "do_objectID": "A08071AE-E450-44E0-9CAB-1B206BD97250",
    "endMarkerType": 0,
    "miterLimit": 10,
    "startMarkerType": 0,
    "textStyle": {
      "_class": "textStyle",
      "do_objectID": "0D627548-9A43-4FFC-8FB5-399E9EB67E6B",
      "encodedAttributes": {
        "MSAttributedStringColorAttribute": {
          "_class": "color",
          "alpha": 1,
          "blue": 0.3333333333333333,
          "green": 0.3333333333333333,
          "red": 0.3333333333333333
        },
        "MSAttributedStringFontAttribute": {
          "_class": "fontDescriptor",
          "attributes": {
            "name": "OpenSans",
            "size": 12
          }
        },
        "paragraphStyle": {
          "_class": "paragraphStyle",
          "alignment": 0,
          "maximumLineHeight": 16,
          "minimumLineHeight": 16
        },
        "textStyleVerticalAlignmentKey": 0
      },
      "verticalAlignment": 0
    },
    "windingRule": 1
  },
  "textBehaviour": 0,
  "userInfo": {
    "com.animaapp.stc-sketch-plugin": {
      "kModelPropertiesKey": {
        "isAutoWidth": 0
      }
    }
  }
}