{
  "_class": "symbolInstance",
  "booleanOperation": -1,
  "clippingMaskMode": 0,
  "do_objectID": "532F9787-B28F-4D71-922A-0867AAC254CE",
  "exportOptions": {
    "_class": "exportOptions",
    "do_objectID": "C78DF8F5-C468-42C0-8CD9-AF11CC7A7A0A",
    "exportFormats": [
    ],
    "includedLayerIds": [
    ],
    "layerOptions": 0,
    "shouldTrim": false
  },
  "frame": {
    "_class": "rect",
    "constrainProportions": false,
    "do_objectID": "16C84826-625F-421F-921C-34AB38F40478",
    "height": 1,
    "width": 1024,
    "x": 0,
    "y": 55
  },
  "hasClippingMask": false,
  "horizontalSpacing": 0,
  "isFixedToViewport": false,
  "isFlippedHorizontal": false,
  "isFlippedVertical": false,
  "isLocked": false,
  "isVisible": false,
  "layerListExpandedType": 0,
  "name": "border",
  "nameIsFixed": false,
  "overrideValues": [
  ],
  "resizingConstraint": 63,
  "resizingType": 0,
  "rotation": 0,
  "scale": 1,
  "shouldBreakMaskChain": false,
  "style": {
    "_class": "style",
    "do_objectID": "2AB8F379-971C-4F0E-9C75-4F712FD0C6E2",
    "endMarkerType": 0,
    "miterLimit": 10,
    "startMarkerType": 0,
    "windingRule": 1
  },
  "symbolID": "A87719B1-9DD4-4B75-9F17-8AB53413005C",
  "verticalSpacing": 0
}