{
  "_class": "group",
  "booleanOperation": 0,
  "clippingMaskMode": 0,
  "do_objectID": "CE4A019F-A98E-41D2-B3A2-F16B9E4EFA48",
  "exportOptions": {
    "_class": "exportOptions",
    "do_objectID": "C818879A-505B-4FA1-91FA-8032A08306D9",
    "exportFormats": [
    ],
    "includedLayerIds": [
    ],
    "layerOptions": 0,
    "shouldTrim": false
  },
  "frame": {
    "_class": "rect",
    "constrainProportions": false,
    "do_objectID": "E19481A1-81A6-4875-BFDE-15EBCCE442DC",
    "height": 100,
    "width": 100,
    "x": 0,
    "y": 0
  },
  "groupLayout": {
    "_class": "MSImmutableFreeformGroupLayout",
    "do_objectID": "E391FEE7-95D4-47CE-89D5-D357E1A973F8"
  },
  "hasClickThrough": false,
  "hasClippingMask": false,
  "isFixedToViewport": false,
  "isFlippedHorizontal": false,
  "isFlippedVertical": false,
  "isLocked": false,
  "isVisible": true,
  "layerListExpandedType": 2,
  "layers": [
    {
      "class": "rectangle",
      "id": "6A142490-09DC-49D9-9F61-89F792996785"
    }
  ],
  "name": "Fill",
  "nameIsFixed": true,
  "resizingConstraint": 63,
  "resizingType": 0,
  "rotation": 0,
  "shouldBreakMaskChain": false,
  "style": {
    "_class": "style",
    "do_objectID": "AD0C9988-FBD0-42FE-85C6-141BDDFD08E0",
    "endMarkerType": 0,
    "miterLimit": 10,
    "startMarkerType": 0,
    "windingRule": 1
  }
}